pipeline_mermaid/__init__.py
pipeline_mermaid/generators.py
pipeline_mermaid/gitlab_helper.py
pipeline_mermaid/gitlab_utils.py
pipeline_mermaid-0.5.data/scripts/pipeline-mermaid
pipeline_mermaid-0.5.dist-info/LICENSE.txt
pipeline_mermaid-0.5.dist-info/METADATA
pipeline_mermaid-0.5.dist-info/WHEEL
pipeline_mermaid-0.5.dist-info/top_level.txt
pipeline_mermaid-0.5.dist-info/RECORD
