Metadata-Version: 2.1
Name: pipeline-mermaid
Version: 0.5
Summary: Useful tool to show Gitlab pipeline as mermaid
Home-page: https://github.com/Nov1kov/pipeline_to_mermaid
Author: Ivan Novikov
Author-email: spellh1@gmail.com
License: MIT
Download-URL: https://pypi.org/project/pipeline-mermaid/
Keywords: pipeline,mermaid,Gitlab
Platform: UNKNOWN
Requires-Dist: python-gitlab
